test/__init__.py
test/test_billing.py
test/test_config.py
test/test_customerVault.py
test/test_pay.py
test/test_plans.py
test/test_subscriptions.py
wknmi/__init__.py
wknmi/auth.py
wknmi/billing.py
wknmi/config.py
wknmi/customer_vault.py
wknmi/payment.py
wknmi/plans.py
wknmi/subscriptions.py
wkl_nmi-0.0.12.dist-info/LICENSE
wkl_nmi-0.0.12.dist-info/METADATA
wkl_nmi-0.0.12.dist-info/WHEEL
wkl_nmi-0.0.12.dist-info/top_level.txt
wkl_nmi-0.0.12.dist-info/RECORD
